{"total":45,"pageSize":12,"pageCount":4,"data":[{"title":"Winning 住院病历","uid":"5fc3c8705ea835b2bb6930af6ce60158","slug":"winning 住院病历","date":"2024-12-30T15:48:51.199Z","updated":"2024-12-31T14:42:34.000Z","comments":true,"path":"api/articles/winning 住院病历.json","keywords":null,"cover":[],"text":"1 住院病历1.住院病历组成 2.会诊申请流程 会诊申请科室填写会诊申请一&gt;会诊接收后答复一&gt;会诊接收科室填写会诊反馈一&gt;会诊申请科室反馈一&...","permalink":"/post/winning 住院病历","photos":[],"count_time":{"symbolsCount":471,"symbolsTime":"1 mins."},"categories":[{"name":"工作","slug":"工作","count":9,"path":"api/categories/工作.json"}],"tags":[{"name":"工作","slug":"工作","count":8,"path":"api/tags/工作.json"}],"author":{"name":"Vegetabhl","slug":"blog-author","avatar":"https://raw.githubusercontent.com/Vegetabhl/Images/master/img/avatar_1.jpg","link":"/","description":"--欢迎来到小卜同学的小破站--     Welcome to Xiaobu’s little website","socials":{"github":"https://github.com/Vegetabhl","twitter":"","stackoverflow":"","wechat":"","qq":"","weibo":"","zhihu":"","csdn":"","juejin":"","customs":{"bilibili":{"icon":"/svg/bilibili.svg","link":"https://space.bilibili.com/398361872"},"wechat":{"icon":"/svg/wx.svg","link":"https://raw.githubusercontent.com/Vegetabhl/Images/master/img/wx.jpg"}}}},"feature":null},{"title":"Winning 药房、药库系统","uid":"4f29ce88c66bb19bbd3457ec6add2391","slug":"Winning 药房、药库系统","date":"2024-12-28T14:35:06.284Z","updated":"2024-12-28T14:42:40.440Z","comments":true,"path":"api/articles/Winning 药房、药库系统.json","keywords":null,"cover":"https://vegetabhlimg.netlify.app/img/3cfb8cd187864127879741d61c2c20e5_2.png","text":"[TOC] 1 药品字典基本维护 1.1 临床目录在(药库管理一&gt;设置一&gt;药品临床目录设置)模块 1.2 规格目录规格目录、产地目录字典的维护都在(...","permalink":"/post/Winning 药房、药库系统","photos":[],"count_time":{"symbolsCount":"2k","symbolsTime":"2 mins."},"categories":[{"name":"工作","slug":"工作","count":9,"path":"api/categories/工作.json"}],"tags":[{"name":"工作","slug":"工作","count":8,"path":"api/tags/工作.json"}],"author":{"name":"Vegetabhl","slug":"blog-author","avatar":"https://raw.githubusercontent.com/Vegetabhl/Images/master/img/avatar_1.jpg","link":"/","description":"--欢迎来到小卜同学的小破站--     Welcome to Xiaobu’s little website","socials":{"github":"https://github.com/Vegetabhl","twitter":"","stackoverflow":"","wechat":"","qq":"","weibo":"","zhihu":"","csdn":"","juejin":"","customs":{"bilibili":{"icon":"/svg/bilibili.svg","link":"https://space.bilibili.com/398361872"},"wechat":{"icon":"/svg/wx.svg","link":"https://raw.githubusercontent.com/Vegetabhl/Images/master/img/wx.jpg"}}}},"feature":null},{"title":"Winning 人员基本信息维护&权限添加","uid":"bd8dc2dc805bea8f596381ac4c12c817","slug":"Winning 人员基本信息维护&权限添加","date":"2024-12-23T14:30:13.223Z","updated":"2024-12-28T14:38:17.821Z","comments":true,"path":"api/articles/Winning 人员基本信息维护&权限添加.json","keywords":null,"cover":"https://vegetabhlimg.netlify.app/img/004b6a43b7e7427eb98e1c000f9e7a62_1.png","text":"人员基本信息维护&amp;权限添加1 医生基本信息维护和权限添加1.1 职工信息登记-分配权限 这里科室、病区都添加只是控制的默认登录设置，只要登录的话执行1....","permalink":"/post/Winning 人员基本信息维护&权限添加","photos":[],"count_time":{"symbolsCount":670,"symbolsTime":"1 mins."},"categories":[{"name":"工作","slug":"工作","count":9,"path":"api/categories/工作.json"}],"tags":[{"name":"工作","slug":"工作","count":8,"path":"api/tags/工作.json"}],"author":{"name":"Vegetabhl","slug":"blog-author","avatar":"https://raw.githubusercontent.com/Vegetabhl/Images/master/img/avatar_1.jpg","link":"/","description":"--欢迎来到小卜同学的小破站--     Welcome to Xiaobu’s little website","socials":{"github":"https://github.com/Vegetabhl","twitter":"","stackoverflow":"","wechat":"","qq":"","weibo":"","zhihu":"","csdn":"","juejin":"","customs":{"bilibili":{"icon":"/svg/bilibili.svg","link":"https://space.bilibili.com/398361872"},"wechat":{"icon":"/svg/wx.svg","link":"https://raw.githubusercontent.com/Vegetabhl/Images/master/img/wx.jpg"}}}},"feature":null},{"title":"《挂号收费出入院》练习指引路径","uid":"e0749a230089fbaecf273d937919b50f","slug":"《挂号收费出入院》练习指引路径","date":"2024-11-21T14:53:20.380Z","updated":"2024-11-21T14:52:13.245Z","comments":true,"path":"api/articles/《挂号收费出入院》练习指引路径.json","keywords":null,"cover":"https://vegetabhlimg.netlify.app/img/85e361e1166246d98faaad2591efb1e4_1.png","text":"《挂号收费出入院》练习指引路径 序号 模块 模块内容 1 基本信息登记 基本信息登记界面，刷卡、读卡或读身份证，补全必填信息 2 基本信息维护 基本信息维护菜单...","permalink":"/post/《挂号收费出入院》练习指引路径","photos":[],"count_time":{"symbolsCount":"1.2k","symbolsTime":"1 mins."},"categories":[{"name":"工作","slug":"工作","count":9,"path":"api/categories/工作.json"}],"tags":[{"name":"工作","slug":"工作","count":8,"path":"api/tags/工作.json"}],"author":{"name":"Vegetabhl","slug":"blog-author","avatar":"https://raw.githubusercontent.com/Vegetabhl/Images/master/img/avatar_1.jpg","link":"/","description":"--欢迎来到小卜同学的小破站--     Welcome to Xiaobu’s little website","socials":{"github":"https://github.com/Vegetabhl","twitter":"","stackoverflow":"","wechat":"","qq":"","weibo":"","zhihu":"","csdn":"","juejin":"","customs":{"bilibili":{"icon":"/svg/bilibili.svg","link":"https://space.bilibili.com/398361872"},"wechat":{"icon":"/svg/wx.svg","link":"https://raw.githubusercontent.com/Vegetabhl/Images/master/img/wx.jpg"}}}},"feature":null},{"title":"Winning Health","uid":"f3b2e5de3bb3466e90ad92e6ab572687","slug":"Winning Health","date":"2024-10-14T13:05:41.951Z","updated":"2024-12-28T14:40:05.301Z","comments":true,"path":"api/articles/Winning Health.json","keywords":null,"cover":"https://vegetabhlimg.netlify.app/img/2f70d0482b4946678682e5c02c9abd32_1.png","text":"[TOC] 0 系统安装0.1 各科室安装需求 系统 科室 HIS 护士站、药房、收款室、所有辅助科室和行政科室 门诊医生站 门诊医生站、住院医生站 住院医生站...","permalink":"/post/Winning Health","photos":[],"count_time":{"symbolsCount":"10k","symbolsTime":"9 mins."},"categories":[{"name":"工作","slug":"工作","count":9,"path":"api/categories/工作.json"}],"tags":[{"name":"工作","slug":"工作","count":8,"path":"api/tags/工作.json"}],"author":{"name":"Vegetabhl","slug":"blog-author","avatar":"https://raw.githubusercontent.com/Vegetabhl/Images/master/img/avatar_1.jpg","link":"/","description":"--欢迎来到小卜同学的小破站--     Welcome to Xiaobu’s little website","socials":{"github":"https://github.com/Vegetabhl","twitter":"","stackoverflow":"","wechat":"","qq":"","weibo":"","zhihu":"","csdn":"","juejin":"","customs":{"bilibili":{"icon":"/svg/bilibili.svg","link":"https://space.bilibili.com/398361872"},"wechat":{"icon":"/svg/wx.svg","link":"https://raw.githubusercontent.com/Vegetabhl/Images/master/img/wx.jpg"}}}},"feature":null},{"title":"sql server共享目录等相关路径无法更改","uid":"e0678d96ea5517903ec41e8e23a94999","slug":"sql server共享目录等相关路径无法更改","date":"2024-07-25T13:08:45.761Z","updated":"2024-12-23T14:37:15.366Z","comments":true,"path":"api/articles/sql server共享目录等相关路径无法更改.json","keywords":null,"cover":"https://vegetabhlimg.netlify.app/img/e7bfd54722c947fd91aa2b0ce45de2ac_3.png","text":"注意：什么路径不可改就搜索该路径进行删除注册表记录，然后重启电脑 按 win 键盘 + R 输入 regedit 进去注册表，点击计算机按 “编辑”–》查找下一...","permalink":"/post/sql server共享目录等相关路径无法更改","photos":[],"count_time":{"symbolsCount":357,"symbolsTime":"1 mins."},"categories":[],"tags":[],"author":{"name":"Vegetabhl","slug":"blog-author","avatar":"https://raw.githubusercontent.com/Vegetabhl/Images/master/img/avatar_1.jpg","link":"/","description":"--欢迎来到小卜同学的小破站--     Welcome to Xiaobu’s little website","socials":{"github":"https://github.com/Vegetabhl","twitter":"","stackoverflow":"","wechat":"","qq":"","weibo":"","zhihu":"","csdn":"","juejin":"","customs":{"bilibili":{"icon":"/svg/bilibili.svg","link":"https://space.bilibili.com/398361872"},"wechat":{"icon":"/svg/wx.svg","link":"https://raw.githubusercontent.com/Vegetabhl/Images/master/img/wx.jpg"}}}},"feature":null},{"title":"ubuntu日常使用","uid":"fd29a6255ba6815d7a29c88dd74c9f39","slug":"ubuntu日常使用","date":"2024-06-11T14:30:45.836Z","updated":"2024-12-23T14:36:09.656Z","comments":true,"path":"api/articles/ubuntu日常使用.json","keywords":null,"cover":"https://vegetabhlimg.netlify.app/img/b46a7397ea394c7a9e30f912064b47ad_1.png","text":"ubuntu日常使用网上下载安装的程序统一放在~&#x2F;soft目录下 本文所有操作全部基于ubuntu20.04版本 [TOC] 0 常用命令和快捷键12...","permalink":"/post/ubuntu日常使用","photos":[],"count_time":{"symbolsCount":"11k","symbolsTime":"10 mins."},"categories":[{"name":"操作系统","slug":"操作系统","count":1,"path":"api/categories/操作系统.json"},{"name":"网络","slug":"操作系统/网络","count":1,"path":"api/categories/操作系统/网络.json"},{"name":"常用工具","slug":"操作系统/网络/常用工具","count":1,"path":"api/categories/操作系统/网络/常用工具.json"},{"name":"项目","slug":"操作系统/网络/常用工具/项目","count":1,"path":"api/categories/操作系统/网络/常用工具/项目.json"},{"name":"环境配置","slug":"操作系统/网络/常用工具/项目/环境配置","count":1,"path":"api/categories/操作系统/网络/常用工具/项目/环境配置.json"},{"name":"docker","slug":"操作系统/网络/常用工具/项目/环境配置/docker","count":1,"path":"api/categories/操作系统/网络/常用工具/项目/环境配置/docker.json"}],"tags":[{"name":"操作系统","slug":"操作系统","count":3,"path":"api/tags/操作系统.json"},{"name":"网络","slug":"网络","count":6,"path":"api/tags/网络.json"},{"name":"常用工具","slug":"常用工具","count":6,"path":"api/tags/常用工具.json"},{"name":"项目","slug":"项目","count":5,"path":"api/tags/项目.json"},{"name":"环境配置","slug":"环境配置","count":5,"path":"api/tags/环境配置.json"},{"name":"docker","slug":"docker","count":4,"path":"api/tags/docker.json"}],"author":{"name":"Vegetabhl","slug":"blog-author","avatar":"https://raw.githubusercontent.com/Vegetabhl/Images/master/img/avatar_1.jpg","link":"/","description":"--欢迎来到小卜同学的小破站--     Welcome to Xiaobu’s little website","socials":{"github":"https://github.com/Vegetabhl","twitter":"","stackoverflow":"","wechat":"","qq":"","weibo":"","zhihu":"","csdn":"","juejin":"","customs":{"bilibili":{"icon":"/svg/bilibili.svg","link":"https://space.bilibili.com/398361872"},"wechat":{"icon":"/svg/wx.svg","link":"https://raw.githubusercontent.com/Vegetabhl/Images/master/img/wx.jpg"}}}},"feature":null},{"title":"华为IA-IE","uid":"5a30a74d412d8315491a167b8e238a38","slug":"华为IA-IE","date":"2024-06-06T14:12:13.456Z","updated":"2024-06-06T15:12:41.769Z","comments":true,"path":"api/articles/华为IA-IE.json","keywords":null,"cover":null,"text":"华为IA-IE","permalink":"/post/华为IA-IE","photos":[],"count_time":{"symbolsCount":7,"symbolsTime":"1 mins."},"categories":[{"name":"工作","slug":"工作","count":9,"path":"api/categories/工作.json"},{"name":"网络","slug":"工作/网络","count":2,"path":"api/categories/工作/网络.json"},{"name":"项目","slug":"工作/网络/项目","count":1,"path":"api/categories/工作/网络/项目.json"}],"tags":[{"name":"网络","slug":"网络","count":6,"path":"api/tags/网络.json"},{"name":"常用工具","slug":"常用工具","count":6,"path":"api/tags/常用工具.json"},{"name":"项目","slug":"项目","count":5,"path":"api/tags/项目.json"}],"author":{"name":"Vegetabhl","slug":"blog-author","avatar":"https://raw.githubusercontent.com/Vegetabhl/Images/master/img/avatar_1.jpg","link":"/","description":"--欢迎来到小卜同学的小破站--     Welcome to Xiaobu’s little website","socials":{"github":"https://github.com/Vegetabhl","twitter":"","stackoverflow":"","wechat":"","qq":"","weibo":"","zhihu":"","csdn":"","juejin":"","customs":{"bilibili":{"icon":"/svg/bilibili.svg","link":"https://space.bilibili.com/398361872"},"wechat":{"icon":"/svg/wx.svg","link":"https://raw.githubusercontent.com/Vegetabhl/Images/master/img/wx.jpg"}}}},"feature":null},{"title":"Excel数据位置匹配","uid":"77f66672ba9a793de02312a2e6c233c6","slug":"Excel数据位置匹配","date":"2024-06-03T17:17:36.289Z","updated":"2024-06-03T17:17:23.301Z","comments":true,"path":"api/articles/Excel数据位置匹配.json","keywords":null,"cover":"https://vegetabhlimg.netlify.app/img/b6690409c7d740f9b6279fb07203d93a_2.png","text":"Excel数据位置匹配1.1 原始数据处理 数据列先移动到单元格最上面位置不要动. 复制对应标签。 复制对应标签。 注意步骤先后顺序。 1.2 Excel数据位...","permalink":"/post/Excel数据位置匹配","photos":[],"count_time":{"symbolsCount":488,"symbolsTime":"1 mins."},"categories":[{"name":"工作","slug":"工作","count":9,"path":"api/categories/工作.json"},{"name":"常用工具","slug":"工作/常用工具","count":1,"path":"api/categories/工作/常用工具.json"}],"tags":[{"name":"工作","slug":"工作","count":8,"path":"api/tags/工作.json"},{"name":"常用工具","slug":"常用工具","count":6,"path":"api/tags/常用工具.json"}],"author":{"name":"Vegetabhl","slug":"blog-author","avatar":"https://raw.githubusercontent.com/Vegetabhl/Images/master/img/avatar_1.jpg","link":"/","description":"--欢迎来到小卜同学的小破站--     Welcome to Xiaobu’s little website","socials":{"github":"https://github.com/Vegetabhl","twitter":"","stackoverflow":"","wechat":"","qq":"","weibo":"","zhihu":"","csdn":"","juejin":"","customs":{"bilibili":{"icon":"/svg/bilibili.svg","link":"https://space.bilibili.com/398361872"},"wechat":{"icon":"/svg/wx.svg","link":"https://raw.githubusercontent.com/Vegetabhl/Images/master/img/wx.jpg"}}}},"feature":null},{"title":"Linux","uid":"3fe1ee3f3830128bf539e5f4ed9fbbe9","slug":"Linux","date":"2024-05-26T12:13:16.439Z","updated":"2024-05-29T15:19:21.465Z","comments":true,"path":"api/articles/Linux.json","keywords":null,"cover":[],"text":"Linux 1234567891011121314151617181920/（根目录）：文件系统的根目录，所有其他目录和文件都位于此目录下。/bin（Binar...","permalink":"/post/Linux","photos":[],"count_time":{"symbolsCount":"2.8k","symbolsTime":"3 mins."},"categories":[],"tags":[],"author":{"name":"Vegetabhl","slug":"blog-author","avatar":"https://raw.githubusercontent.com/Vegetabhl/Images/master/img/avatar_1.jpg","link":"/","description":"--欢迎来到小卜同学的小破站--     Welcome to Xiaobu’s little website","socials":{"github":"https://github.com/Vegetabhl","twitter":"","stackoverflow":"","wechat":"","qq":"","weibo":"","zhihu":"","csdn":"","juejin":"","customs":{"bilibili":{"icon":"/svg/bilibili.svg","link":"https://space.bilibili.com/398361872"},"wechat":{"icon":"/svg/wx.svg","link":"https://raw.githubusercontent.com/Vegetabhl/Images/master/img/wx.jpg"}}}},"feature":null},{"title":"3-DQL查询语句、约束、多表关系、范式、数据库备份和还原","uid":"ba3795bcaa1c4cf0d23951d6953d8fd5","slug":"3-DQL查询语句、约束、多表关系、范式、数据库备份和还原","date":"2024-05-01T11:43:02.716Z","updated":"2024-05-01T11:41:29.940Z","comments":true,"path":"api/articles/3-DQL查询语句、约束、多表关系、范式、数据库备份和还原.json","keywords":null,"cover":null,"text":"3-DQL查询语句、约束、多表关系、范式、数据库备份和还原txt1. DQL:查询语句 1. 排序查询 2. 聚合函数 3. 分组查询 4. 分页查询 2. 约...","permalink":"/post/3-DQL查询语句、约束、多表关系、范式、数据库备份和还原","photos":[],"count_time":{"symbolsCount":"7.6k","symbolsTime":"7 mins."},"categories":[{"name":"mysql","slug":"mysql","count":3,"path":"api/categories/mysql.json"}],"tags":[{"name":"mysql","slug":"mysql","count":3,"path":"api/tags/mysql.json"}],"author":{"name":"Vegetabhl","slug":"blog-author","avatar":"https://raw.githubusercontent.com/Vegetabhl/Images/master/img/avatar_1.jpg","link":"/","description":"--欢迎来到小卜同学的小破站--     Welcome to Xiaobu’s little website","socials":{"github":"https://github.com/Vegetabhl","twitter":"","stackoverflow":"","wechat":"","qq":"","weibo":"","zhihu":"","csdn":"","juejin":"","customs":{"bilibili":{"icon":"/svg/bilibili.svg","link":"https://space.bilibili.com/398361872"},"wechat":{"icon":"/svg/wx.svg","link":"https://raw.githubusercontent.com/Vegetabhl/Images/master/img/wx.jpg"}}}},"feature":null},{"title":"2-DQL多表查询、事务、DCL(管理用户和授权)","uid":"9c31673e0471abc8c04ba8eee1f127f7","slug":"2-DQL多表查询、事务、DCL(管理用户和授权)","date":"2024-05-01T11:43:02.714Z","updated":"2024-05-01T11:41:16.830Z","comments":true,"path":"api/articles/2-DQL多表查询、事务、DCL(管理用户和授权).json","keywords":null,"cover":null,"text":"2-DQL多表查询、事务、DCL(管理用户和授权)txt1. 多表查询 2. 事务 3. DCL多表查询：txt* 查询语法： select 列名列表 from...","permalink":"/post/2-DQL多表查询、事务、DCL(管理用户和授权)","photos":[],"count_time":{"symbolsCount":"14k","symbolsTime":"13 mins."},"categories":[{"name":"mysql","slug":"mysql","count":3,"path":"api/categories/mysql.json"}],"tags":[{"name":"mysql","slug":"mysql","count":3,"path":"api/tags/mysql.json"}],"author":{"name":"Vegetabhl","slug":"blog-author","avatar":"https://raw.githubusercontent.com/Vegetabhl/Images/master/img/avatar_1.jpg","link":"/","description":"--欢迎来到小卜同学的小破站--     Welcome to Xiaobu’s little website","socials":{"github":"https://github.com/Vegetabhl","twitter":"","stackoverflow":"","wechat":"","qq":"","weibo":"","zhihu":"","csdn":"","juejin":"","customs":{"bilibili":{"icon":"/svg/bilibili.svg","link":"https://space.bilibili.com/398361872"},"wechat":{"icon":"/svg/wx.svg","link":"https://raw.githubusercontent.com/Vegetabhl/Images/master/img/wx.jpg"}}}},"feature":null}]}