{"name":"常用工具","slug":"常用工具","count":6,"postlist":[{"title":"ubuntu日常使用","uid":"fd29a6255ba6815d7a29c88dd74c9f39","slug":"ubuntu日常使用","date":"2024-06-11T14:30:45.836Z","updated":"2024-12-23T14:36:09.656Z","comments":true,"path":"api/articles/ubuntu日常使用.json","keywords":null,"cover":"https://vegetabhlimg.netlify.app/img/b46a7397ea394c7a9e30f912064b47ad_1.png","text":"ubuntu日常使用网上下载安装的程序统一放在~&#x2F;soft目录下 本文所有操作全部基于ubuntu20.04版本 [TOC] 0 常用命令和快捷键12...","permalink":"/post/ubuntu日常使用","photos":[],"count_time":{"symbolsCount":"11k","symbolsTime":"10 mins."},"categories":[{"name":"操作系统","slug":"操作系统","count":1,"path":"api/categories/操作系统.json"},{"name":"网络","slug":"操作系统/网络","count":1,"path":"api/categories/操作系统/网络.json"},{"name":"常用工具","slug":"操作系统/网络/常用工具","count":1,"path":"api/categories/操作系统/网络/常用工具.json"},{"name":"项目","slug":"操作系统/网络/常用工具/项目","count":1,"path":"api/categories/操作系统/网络/常用工具/项目.json"},{"name":"环境配置","slug":"操作系统/网络/常用工具/项目/环境配置","count":1,"path":"api/categories/操作系统/网络/常用工具/项目/环境配置.json"},{"name":"docker","slug":"操作系统/网络/常用工具/项目/环境配置/docker","count":1,"path":"api/categories/操作系统/网络/常用工具/项目/环境配置/docker.json"}],"tags":[{"name":"操作系统","slug":"操作系统","count":3,"path":"api/tags/操作系统.json"},{"name":"网络","slug":"网络","count":6,"path":"api/tags/网络.json"},{"name":"常用工具","slug":"常用工具","count":6,"path":"api/tags/常用工具.json"},{"name":"项目","slug":"项目","count":5,"path":"api/tags/项目.json"},{"name":"环境配置","slug":"环境配置","count":5,"path":"api/tags/环境配置.json"},{"name":"docker","slug":"docker","count":4,"path":"api/tags/docker.json"}],"author":{"name":"Vegetabhl","slug":"blog-author","avatar":"https://raw.githubusercontent.com/Vegetabhl/Images/master/img/avatar_1.jpg","link":"/","description":"--欢迎来到小卜同学的小破站--     Welcome to Xiaobu’s little website","socials":{"github":"https://github.com/Vegetabhl","twitter":"","stackoverflow":"","wechat":"","qq":"","weibo":"","zhihu":"","csdn":"","juejin":"","customs":{"bilibili":{"icon":"/svg/bilibili.svg","link":"https://space.bilibili.com/398361872"},"wechat":{"icon":"/svg/wx.svg","link":"https://raw.githubusercontent.com/Vegetabhl/Images/master/img/wx.jpg"}}}},"feature":null},{"title":"华为IA-IE","uid":"5a30a74d412d8315491a167b8e238a38","slug":"华为IA-IE","date":"2024-06-06T14:12:13.456Z","updated":"2024-06-06T15:12:41.769Z","comments":true,"path":"api/articles/华为IA-IE.json","keywords":null,"cover":null,"text":"华为IA-IE","permalink":"/post/华为IA-IE","photos":[],"count_time":{"symbolsCount":7,"symbolsTime":"1 mins."},"categories":[{"name":"工作","slug":"工作","count":8,"path":"api/categories/工作.json"},{"name":"网络","slug":"工作/网络","count":2,"path":"api/categories/工作/网络.json"},{"name":"项目","slug":"工作/网络/项目","count":1,"path":"api/categories/工作/网络/项目.json"}],"tags":[{"name":"网络","slug":"网络","count":6,"path":"api/tags/网络.json"},{"name":"常用工具","slug":"常用工具","count":6,"path":"api/tags/常用工具.json"},{"name":"项目","slug":"项目","count":5,"path":"api/tags/项目.json"}],"author":{"name":"Vegetabhl","slug":"blog-author","avatar":"https://raw.githubusercontent.com/Vegetabhl/Images/master/img/avatar_1.jpg","link":"/","description":"--欢迎来到小卜同学的小破站--     Welcome to Xiaobu’s little website","socials":{"github":"https://github.com/Vegetabhl","twitter":"","stackoverflow":"","wechat":"","qq":"","weibo":"","zhihu":"","csdn":"","juejin":"","customs":{"bilibili":{"icon":"/svg/bilibili.svg","link":"https://space.bilibili.com/398361872"},"wechat":{"icon":"/svg/wx.svg","link":"https://raw.githubusercontent.com/Vegetabhl/Images/master/img/wx.jpg"}}}},"feature":null},{"title":"Excel数据位置匹配","uid":"77f66672ba9a793de02312a2e6c233c6","slug":"Excel数据位置匹配","date":"2024-06-03T17:17:36.289Z","updated":"2024-06-03T17:17:23.301Z","comments":true,"path":"api/articles/Excel数据位置匹配.json","keywords":null,"cover":"https://vegetabhlimg.netlify.app/img/b6690409c7d740f9b6279fb07203d93a_2.png","text":"Excel数据位置匹配1.1 原始数据处理 数据列先移动到单元格最上面位置不要动. 复制对应标签。 复制对应标签。 注意步骤先后顺序。 1.2 Excel数据位...","permalink":"/post/Excel数据位置匹配","photos":[],"count_time":{"symbolsCount":488,"symbolsTime":"1 mins."},"categories":[{"name":"工作","slug":"工作","count":8,"path":"api/categories/工作.json"},{"name":"常用工具","slug":"工作/常用工具","count":1,"path":"api/categories/工作/常用工具.json"}],"tags":[{"name":"工作","slug":"工作","count":7,"path":"api/tags/工作.json"},{"name":"常用工具","slug":"常用工具","count":6,"path":"api/tags/常用工具.json"}],"author":{"name":"Vegetabhl","slug":"blog-author","avatar":"https://raw.githubusercontent.com/Vegetabhl/Images/master/img/avatar_1.jpg","link":"/","description":"--欢迎来到小卜同学的小破站--     Welcome to Xiaobu’s little website","socials":{"github":"https://github.com/Vegetabhl","twitter":"","stackoverflow":"","wechat":"","qq":"","weibo":"","zhihu":"","csdn":"","juejin":"","customs":{"bilibili":{"icon":"/svg/bilibili.svg","link":"https://space.bilibili.com/398361872"},"wechat":{"icon":"/svg/wx.svg","link":"https://raw.githubusercontent.com/Vegetabhl/Images/master/img/wx.jpg"}}}},"feature":null},{"title":"Front-Meta","uid":"4221a34b979b72d1889277d8691d3068","slug":"1_Front-Meta","date":"2023-12-29T18:59:23.846Z","updated":"2024-06-09T14:59:16.099Z","comments":true,"path":"api/articles/1_Front-Meta.json","keywords":null,"cover":"https://vegetabhlimg.netlify.app/img/b6690409c7d740f9b6279fb07203d93a_2.png","text":"Front-Meta测试专属页面 ","permalink":"/post/1_Front-Meta","photos":[],"count_time":{"symbolsCount":17,"symbolsTime":"1 mins."},"categories":[{"name":"工作","slug":"工作","count":8,"path":"api/categories/工作.json"},{"name":"Python","slug":"工作/Python","count":1,"path":"api/categories/工作/Python.json"},{"name":"Java","slug":"工作/Python/Java","count":1,"path":"api/categories/工作/Python/Java.json"},{"name":"deep learning","slug":"工作/Python/Java/deep-learning","count":1,"path":"api/categories/工作/Python/Java/deep-learning.json"},{"name":"操作系统","slug":"工作/Python/Java/deep-learning/操作系统","count":1,"path":"api/categories/工作/Python/Java/deep-learning/操作系统.json"},{"name":"网络","slug":"工作/Python/Java/deep-learning/操作系统/网络","count":1,"path":"api/categories/工作/Python/Java/deep-learning/操作系统/网络.json"},{"name":"常用工具","slug":"工作/Python/Java/deep-learning/操作系统/网络/常用工具","count":1,"path":"api/categories/工作/Python/Java/deep-learning/操作系统/网络/常用工具.json"},{"name":"项目","slug":"工作/Python/Java/deep-learning/操作系统/网络/常用工具/项目","count":1,"path":"api/categories/工作/Python/Java/deep-learning/操作系统/网络/常用工具/项目.json"},{"name":"环境配置","slug":"工作/Python/Java/deep-learning/操作系统/网络/常用工具/项目/环境配置","count":1,"path":"api/categories/工作/Python/Java/deep-learning/操作系统/网络/常用工具/项目/环境配置.json"},{"name":"docker","slug":"工作/Python/Java/deep-learning/操作系统/网络/常用工具/项目/环境配置/docker","count":1,"path":"api/categories/工作/Python/Java/deep-learning/操作系统/网络/常用工具/项目/环境配置/docker.json"},{"name":"object detection","slug":"工作/Python/Java/deep-learning/操作系统/网络/常用工具/项目/环境配置/docker/object-detection","count":1,"path":"api/categories/工作/Python/Java/deep-learning/操作系统/网络/常用工具/项目/环境配置/docker/object-detection.json"}],"tags":[{"name":"工作","slug":"工作","count":7,"path":"api/tags/工作.json"},{"name":"Python","slug":"Python","count":6,"path":"api/tags/Python.json"},{"name":"Java","slug":"Java","count":3,"path":"api/tags/Java.json"},{"name":"deep learning","slug":"deep-learning","count":4,"path":"api/tags/deep-learning.json"},{"name":"操作系统","slug":"操作系统","count":3,"path":"api/tags/操作系统.json"},{"name":"网络","slug":"网络","count":6,"path":"api/tags/网络.json"},{"name":"常用工具","slug":"常用工具","count":6,"path":"api/tags/常用工具.json"},{"name":"项目","slug":"项目","count":5,"path":"api/tags/项目.json"},{"name":"环境配置","slug":"环境配置","count":5,"path":"api/tags/环境配置.json"},{"name":"docker","slug":"docker","count":4,"path":"api/tags/docker.json"},{"name":"object detection","slug":"object-detection","count":3,"path":"api/tags/object-detection.json"}],"author":{"name":"Vegetabhl","slug":"vegetabhl","avatar":"https://vegetabhlimg.netlify.app/img/avatar_1.jpg","link":"https://vegetabhl.github.io/","description":"Think like an artist, code like an artisan.","socials":{"github":"https://github.com/Vegetabhl","twitter":"","stackoverflow":"","wechat":"","qq":"","weibo":"","zhihu":"","csdn":"","juejin":"","customs":{}}},"feature":false},{"title":"Git使用","uid":"b127aca37c275431a002f8f9388f3525","slug":"Git使用","date":"2022-05-18T03:39:36.000Z","updated":"2024-06-06T15:08:42.988Z","comments":true,"path":"api/articles/Git使用.json","keywords":null,"cover":[],"text":"注意：除非直接克隆，否则记得要先创建仓库，再进行后续的操作Git使用1 TortoiseGit下载和安装 2 TortoiseGit使用1创建仓库先创建一个空文...","permalink":"/post/Git使用","photos":[],"count_time":{"symbolsCount":"1.1k","symbolsTime":"1 mins."},"categories":[{"name":"网络","slug":"网络","count":2,"path":"api/categories/网络.json"},{"name":"常用工具","slug":"网络/常用工具","count":2,"path":"api/categories/网络/常用工具.json"},{"name":"项目","slug":"网络/常用工具/项目","count":2,"path":"api/categories/网络/常用工具/项目.json"},{"name":"环境配置","slug":"网络/常用工具/项目/环境配置","count":2,"path":"api/categories/网络/常用工具/项目/环境配置.json"}],"tags":[{"name":"网络","slug":"网络","count":6,"path":"api/tags/网络.json"},{"name":"常用工具","slug":"常用工具","count":6,"path":"api/tags/常用工具.json"},{"name":"项目","slug":"项目","count":5,"path":"api/tags/项目.json"},{"name":"环境配置","slug":"环境配置","count":5,"path":"api/tags/环境配置.json"}],"author":{"name":"Vegetabhl","slug":"blog-author","avatar":"https://raw.githubusercontent.com/Vegetabhl/Images/master/img/avatar_1.jpg","link":"/","description":"--欢迎来到小卜同学的小破站--     Welcome to Xiaobu’s little website","socials":{"github":"https://github.com/Vegetabhl","twitter":"","stackoverflow":"","wechat":"","qq":"","weibo":"","zhihu":"","csdn":"","juejin":"","customs":{"bilibili":{"icon":"/svg/bilibili.svg","link":"https://space.bilibili.com/398361872"},"wechat":{"icon":"/svg/wx.svg","link":"https://raw.githubusercontent.com/Vegetabhl/Images/master/img/wx.jpg"}}}},"feature":null},{"title":"docker","uid":"4122a09df2e4f3d18921791a0dcc0507","slug":"docker","date":"2021-12-08T08:51:52.984Z","updated":"2024-12-23T14:39:21.377Z","comments":true,"path":"api/articles/docker.json","keywords":null,"cover":"https://vegetabhlimg.netlify.app/img/6f67e43f87f14bb0b2dbafc6b6b844d1_1.png","text":"0 参考12345678910111213141516171819查找镜像：docker search xxx 查看镜像：docker images 看终止状态...","permalink":"/post/docker","photos":[],"count_time":{"symbolsCount":"5.2k","symbolsTime":"5 mins."},"categories":[{"name":"网络","slug":"网络","count":2,"path":"api/categories/网络.json"},{"name":"常用工具","slug":"网络/常用工具","count":2,"path":"api/categories/网络/常用工具.json"},{"name":"项目","slug":"网络/常用工具/项目","count":2,"path":"api/categories/网络/常用工具/项目.json"},{"name":"环境配置","slug":"网络/常用工具/项目/环境配置","count":2,"path":"api/categories/网络/常用工具/项目/环境配置.json"},{"name":"docker","slug":"网络/常用工具/项目/环境配置/docker","count":1,"path":"api/categories/网络/常用工具/项目/环境配置/docker.json"}],"tags":[{"name":"网络","slug":"网络","count":6,"path":"api/tags/网络.json"},{"name":"常用工具","slug":"常用工具","count":6,"path":"api/tags/常用工具.json"},{"name":"项目","slug":"项目","count":5,"path":"api/tags/项目.json"},{"name":"环境配置","slug":"环境配置","count":5,"path":"api/tags/环境配置.json"},{"name":"docker","slug":"docker","count":4,"path":"api/tags/docker.json"}],"author":{"name":"Vegetabhl","slug":"blog-author","avatar":"https://raw.githubusercontent.com/Vegetabhl/Images/master/img/avatar_1.jpg","link":"/","description":"--欢迎来到小卜同学的小破站--     Welcome to Xiaobu’s little website","socials":{"github":"https://github.com/Vegetabhl","twitter":"","stackoverflow":"","wechat":"","qq":"","weibo":"","zhihu":"","csdn":"","juejin":"","customs":{"bilibili":{"icon":"/svg/bilibili.svg","link":"https://space.bilibili.com/398361872"},"wechat":{"icon":"/svg/wx.svg","link":"https://raw.githubusercontent.com/Vegetabhl/Images/master/img/wx.jpg"}}}},"feature":true}]}